Metadata-Version: 2.1
Name: geo-qua
Version: 0.1
Summary: Geometric sequence and quadratic equation
Home-page: UNKNOWN
Author-email: olegisupov542@gmail.com
License: UNKNOWN
Platform: UNKNOWN
